decimalfp/__init__.py
decimalfp/_cdecimalfp.c
decimalfp/_cdecimalfp.cpython-311-darwin.so
decimalfp/_cdecimalfp.pyi
decimalfp/_cdecimalfp_docstrings.h
decimalfp/_pydecimalfp.py
decimalfp/py.typed
decimalfp/rounding.py
decimalfp/version.py
decimalfp/libfpdec/basemath.h
decimalfp/libfpdec/common.h
decimalfp/libfpdec/compiler_macros.h
decimalfp/libfpdec/digit_array.c
decimalfp/libfpdec/digit_array.h
decimalfp/libfpdec/digit_array_struct.h
decimalfp/libfpdec/format_spec.c
decimalfp/libfpdec/format_spec.h
decimalfp/libfpdec/fpdec.c
decimalfp/libfpdec/fpdec.h
decimalfp/libfpdec/fpdec_struct.h
decimalfp/libfpdec/helper_macros.h
decimalfp/libfpdec/mem.h
decimalfp/libfpdec/parser.c
decimalfp/libfpdec/parser.h
decimalfp/libfpdec/rounding.c
decimalfp/libfpdec/rounding.h
decimalfp/libfpdec/rounding_helper.h
decimalfp/libfpdec/shifted_int.c
decimalfp/libfpdec/shifted_int.h
decimalfp/libfpdec/uint128_math.h
decimalfp/libfpdec/uint128_math_native.h
decimalfp/libfpdec/uint128_type.h
decimalfp/libfpdec/uint128_type_native.h
decimalfp/libfpdec/uint64_math.h
decimalfp/libfpdec/unicode_digits.h
decimalfp-0.13.0.dist-info/licenses/LICENCE.txt
decimalfp-0.13.0.dist-info/METADATA
decimalfp-0.13.0.dist-info/WHEEL
decimalfp-0.13.0.dist-info/top_level.txt
decimalfp-0.13.0.dist-info/RECORD
