Metadata-Version: 2.4
Name: decimalfp
Version: 0.13.0
Summary: Decimal numbers with fixed-point arithmetic
Author-email: Michael Amrhein <michael@adrhinum.de>
Project-URL: Homepage, https://github.com/mamrhein/decimalfp
Platform: all
Requires-Python: >=3.11
License-File: LICENCE.txt
Dynamic: license-file
Dynamic: platform
Dynamic: requires-python
